{
  "source": {
    "title": "Copy-of-Eshrit-Al-Hadi-Assamite-S-Door-V.3.5.1",
    "fileName": "Copy-of-Eshrit-Al-Hadi-Assamite-S-Door-V.3.5.1.xlsx",
    "localPath": "source-sheets\\Z-Door-Characters\\Characters\\Assamite\\Copy-of-Eshrit-Al-Hadi-Assamite-S-Door-V.3.5.1.xlsx"
  },
  "folderPath": [
    "Z Door Characters",
    "Characters",
    "Assamite"
  ],
  "coreSheet": "Print Sheet",
  "character": {
    "chronicle": "CHRONICLE",
    "characterName": "Eshrit Al Hadi",
    "playerName": "",
    "gmailAccount": "",
    "clanCoordinator": "Theo Strinz",
    "archetype": "Cultured",
    "title": "",
    "characterStartDate": "",
    "generationLabel": "Pretender Elder 8",
    "clan": "Assamite \"Sorcerer\" - Magical Aura"
  },
  "attributes": {
    "physical": 5,
    "social": 3,
    "mental": 10
  },
  "backgrounds": {
    "generation": 3,
    "herd": 2,
    "resources": 1
  },
  "currentPools": {
    "current_willpower": 6,
    "current_humanity": 5
  },
  "abilities": {
    "investigation": 1,
    "subterfuge": 2,
    "awareness": 2,
    "linguistics": 2,
    "lore": 3,
    "crafts": 1,
    "dodge": 3,
    "occult": 4,
    "firearms": 1,
    "stealth": 1
  },
  "status": [],
  "meritsAndFlaws": [
    "Infernal Power -3",
    "Bloodline Sorcerer -4"
  ],
  "disciplines": [
    {
      "name": "Quietus",
      "value": 1
    },
    {
      "name": "Obfuscate",
      "value": 1
    },
    {
      "name": "Dur-an-ki: Lure of Flames (Hand of the Magi) (C)",
      "value": 2
    }
  ],
  "ritualsRitaeOther": [],
  "abilitySpecializations": [
    "Lore: Demonology, Spirit Names",
    "Lore: Baali",
    "Linguistics: Arabic, Farsi & Egyptian"
  ],
  "rawSheets": {
    "Print Sheet": [
      [
        "",
        "CHRONICLE",
        "",
        "Players Gmail Account:",
        "",
        "",
        "",
        "",
        "BACKGROUNDS",
        "",
        "",
        "",
        "CURRENT POOLS",
        "",
        "48"
      ],
      [
        "",
        "Eshrit Al Hadi",
        "",
        "",
        "",
        "Theo Strinz",
        "",
        "",
        "Generation",
        "3.0",
        "",
        "",
        "Current Willpower",
        "6.0"
      ],
      [
        "",
        "Character Name",
        "",
        "Player Name",
        "",
        "Clan Coordinator",
        "",
        "",
        "Allies",
        "",
        "",
        "",
        "Current Humanity",
        "5.0"
      ],
      [
        "",
        "Cultured",
        "",
        "",
        "",
        "",
        "",
        "",
        "Alternate Identity",
        "",
        "",
        "",
        "Current Blood Points * Per Turn ~ 15*3"
      ],
      [
        "",
        "Archetype",
        "",
        "Title / Political Faction",
        "",
        "Character Start Date",
        "",
        "",
        "Contacts",
        "",
        "",
        "",
        "BACKGROUND NOTES"
      ],
      [
        "",
        "Pretender Elder 8",
        "",
        "Assamite \"Sorcerer\" - Magical Aura",
        "",
        "",
        "",
        "",
        "Fame"
      ],
      [
        "",
        "Generation",
        "",
        "Clan",
        "",
        "",
        "",
        "",
        "Haven"
      ],
      [
        "",
        "ATTRIBUTES",
        "",
        "",
        "",
        "",
        "",
        "",
        "Herd",
        "2.0"
      ],
      [
        "",
        "Physical",
        "5.0",
        "Stamina - No Wound Pen / Can't be Knocked out/down unless less Ptraits",
        "",
        "",
        "",
        "",
        "Influence \"Elite\""
      ],
      [
        "",
        "Social",
        "3.0",
        "Manipulation - +3 Social on Non Power uses dealing with focus.",
        "",
        "",
        "",
        "",
        "Influence \"Underworld\""
      ],
      [
        "",
        "Mental",
        "10.0",
        "Intelligence - +3 Mental on Non Power uses dealing with focus.",
        "",
        "",
        "",
        "",
        "Resources",
        "1.0"
      ],
      [
        "",
        "STATUS",
        "",
        "",
        "",
        "AWARDED BY",
        "",
        "",
        "Retainers"
      ],
      [
        "",
        "",
        "",
        "",
        "",
        "",
        "",
        "",
        "Ritae / Other"
      ],
      [
        "",
        "",
        "",
        "",
        "",
        "",
        "",
        "",
        "MERITS & FLAWS",
        "",
        "",
        "",
        "DISCIPLINES"
      ],
      [
        "",
        "",
        "",
        "",
        "",
        "",
        "",
        "",
        "Infernal Power -3",
        "",
        "",
        "",
        "Quietus",
        "1.0"
      ],
      [
        "",
        "",
        "",
        "",
        "",
        "",
        "",
        "",
        "Bloodline Sorcerer -4",
        "",
        "",
        "",
        "Obfuscate",
        "1.0"
      ],
      [
        "",
        "",
        "",
        "",
        "",
        "",
        "",
        "",
        "",
        "",
        "",
        "",
        "Dur-an-ki: Lure of Flames (Hand of the Magi) (C)",
        "2.0"
      ],
      [
        "",
        "ABILITES",
        "",
        "",
        "",
        "",
        "",
        "",
        "",
        "",
        "",
        "",
        "Dur-an-ki: Hunters Winds (C)",
        "2.0"
      ],
      [
        "",
        "Academics",
        "",
        "Intimidation",
        "",
        "Streetwise",
        "",
        "",
        "",
        "",
        "",
        "",
        "Dur-an-ki: Covenant of Nergal (U)",
        "1.0"
      ],
      [
        "",
        "Animal Ken",
        "",
        "Investigation",
        "1.0",
        "Subterfuge",
        "2.0",
        "",
        "",
        "",
        "",
        "",
        "Dark Thaumaturgy: The Path of Phobos (C)",
        "1.0"
      ],
      [
        "",
        "Athletics",
        "",
        "Leadership",
        "",
        "Survival",
        "",
        "",
        "Former Magus +2"
      ],
      [
        "",
        "Awareness",
        "2.0",
        "Linguistics",
        "2.0",
        "Performance",
        "",
        "",
        "False Amarath +3"
      ],
      [
        "",
        "Brawl",
        "",
        "Lore",
        "3.0",
        "SECONDARY ABILITIES",
        "",
        "",
        "ABILITES FOCUS",
        "",
        "",
        "",
        "RITUALS, RITAE, & OTHER"
      ],
      [
        "",
        "Computer",
        "",
        "Medicine",
        "",
        "",
        "",
        "",
        "Lore: Demonology, Spirit Names"
      ],
      [
        "",
        "Crafts",
        "1.0",
        "Melee",
        "",
        "",
        "",
        "",
        "Lore: Baali"
      ],
      [
        "",
        "Dodge",
        "3.0",
        "Occult",
        "4.0",
        "",
        "",
        "",
        "Linguistics: Arabic, Farsi & Egyptian"
      ],
      [
        "",
        "Drive",
        "",
        "Science"
      ],
      [
        "",
        "Empathy",
        "",
        "Security"
      ],
      [
        "",
        "Firearms",
        "1.0",
        "Stealth",
        "1.0"
      ],
      [
        "",
        "COMMON POOLS"
      ],
      [
        "",
        "Brawl    5",
        "",
        "Dodge    8",
        "",
        "Thaumaturgy -Tals   14"
      ],
      [
        "",
        "Melee    5",
        "",
        "Obfuscate    11",
        "",
        "Thaumaturgy +Tals   16"
      ],
      [
        "",
        "Guns (No Wits)   6",
        "",
        "Quietus    10",
        "",
        "Disciplines Pull Down"
      ],
      [
        "7/5/3 traits, 3/2/1 backgrounds, 2/1/1 disciplines, 4/3/3/2/2/2/1/1/1/1 abilities, 30pts freebie, 7pts merits max, 7pts flaws max - All Merit/Flaw/Freebies must be on XP Spends Sheet",
        "7/5/3 traits, 3/2/1 backgrounds, 2/1/1 disciplines, 4/3/3/2/2/2/1/1/1/1 abilities, 30pts freebie, 7pts merits max, 7pts flaws max - All Merit/Flaw/Freebies must be on XP Spends Sheet",
        "",
        "",
        "",
        "",
        "",
        "",
        "",
        "",
        "",
        "",
        "",
        "3.5.1"
      ]
    ],
    "XP Spends": {
      "rows": [
        [
          "What was bought?",
          "Date",
          "All Costs (+/-)",
          "",
          "",
          "Starting Total XP Left"
        ],
        [
          "Starting XP (30) Point Character",
          "Pre Game",
          "30",
          "",
          "",
          "0"
        ],
        [
          "Infernal Power",
          "Pre Game",
          "-3.0"
        ],
        [
          "Bloodline: Sorcerer",
          "Pre Game",
          "-4.0",
          "",
          "",
          "Total XP Earned"
        ],
        [
          "Former Magus",
          "Pre Game",
          "2.0",
          "",
          "",
          "0"
        ],
        [
          "False Amarath",
          "Pre Game",
          "3.0"
        ],
        [
          "Dur-in-Ka: Covenant of Nergal 1",
          "Pre Game",
          "-3.0",
          "",
          "",
          "Total Games Played"
        ],
        [
          "Dark Thaumaturgy: The Path of Phobos 1",
          "Pre Game",
          "-4.0",
          "",
          "",
          "0"
        ],
        [
          "Dur-in-Ka: Hunters Winds 2",
          "Pre Game",
          "-12.0"
        ],
        [
          "Mental x3",
          "Pre Game",
          "-9.0",
          "",
          "",
          "6 Game XP Earned"
        ],
        [
          "",
          "Pre Game",
          "",
          "",
          "",
          "0"
        ],
        [
          "",
          "Pre Game"
        ],
        [
          "",
          "Pre Game",
          "",
          "",
          "",
          "Current XP Spent"
        ],
        [
          "",
          "Pre Game",
          "",
          "",
          "",
          "0"
        ],
        [
          "",
          "Pre Game"
        ],
        [
          "",
          "Pre Game",
          "",
          "",
          "",
          "Current XP"
        ],
        [
          "",
          "Pre Game",
          "",
          "",
          "",
          "0"
        ],
        [
          "",
          "Pre Game"
        ],
        [
          "If you need to add more cells for character creation. Go to row 18 and add from there to make sure none of the forumulas break."
        ],
        [
          "* Earned XP in Game / Convention Game / 6 Game Bonus XP / What Was Bought *",
          "Date",
          "Bonus Downtimes",
          "Only Postive Numbers"
        ],
        [
          "",
          "",
          "",
          "Earned",
          "Spent"
        ]
      ],
      "records": [
        {
          "what_was_bought": "Starting XP (30) Point Character",
          "date": "Pre Game",
          "all_costs": 30,
          "starting_total_xp_left": 0
        },
        {
          "what_was_bought": "Infernal Power",
          "date": "Pre Game",
          "all_costs": -3
        },
        {
          "what_was_bought": "Bloodline: Sorcerer",
          "date": "Pre Game",
          "all_costs": -4,
          "starting_total_xp_left": "Total XP Earned"
        },
        {
          "what_was_bought": "Former Magus",
          "date": "Pre Game",
          "all_costs": 2,
          "starting_total_xp_left": 0
        },
        {
          "what_was_bought": "False Amarath",
          "date": "Pre Game",
          "all_costs": 3
        },
        {
          "what_was_bought": "Dur-in-Ka: Covenant of Nergal 1",
          "date": "Pre Game",
          "all_costs": -3,
          "starting_total_xp_left": "Total Games Played"
        },
        {
          "what_was_bought": "Dark Thaumaturgy: The Path of Phobos 1",
          "date": "Pre Game",
          "all_costs": -4,
          "starting_total_xp_left": 0
        },
        {
          "what_was_bought": "Dur-in-Ka: Hunters Winds 2",
          "date": "Pre Game",
          "all_costs": -12
        },
        {
          "what_was_bought": "Mental x3",
          "date": "Pre Game",
          "all_costs": -9,
          "starting_total_xp_left": "6 Game XP Earned"
        },
        {
          "date": "Pre Game",
          "starting_total_xp_left": 0
        },
        {
          "date": "Pre Game"
        },
        {
          "date": "Pre Game",
          "starting_total_xp_left": "Current XP Spent"
        },
        {
          "date": "Pre Game",
          "starting_total_xp_left": 0
        },
        {
          "date": "Pre Game"
        },
        {
          "date": "Pre Game",
          "starting_total_xp_left": "Current XP"
        },
        {
          "date": "Pre Game",
          "starting_total_xp_left": 0
        },
        {
          "date": "Pre Game"
        },
        {
          "what_was_bought": "If you need to add more cells for character creation. Go to row 18 and add from there to make sure none of the forumulas break."
        },
        {
          "what_was_bought": "* Earned XP in Game / Convention Game / 6 Game Bonus XP / What Was Bought *",
          "date": "Date",
          "all_costs": "Bonus Downtimes",
          "column_4": "Only Postive Numbers"
        },
        {
          "column_4": "Earned",
          "column_5": "Spent"
        }
      ]
    },
    "History": {
      "rows": [
        [
          "Staff Generated Concept",
          "",
          "",
          "",
          "",
          "",
          "",
          "",
          "Created By:"
        ],
        [
          "You were a mage you controled reality and were a strong warrior in the wars of ascention. But then you learned the most demoralizing truth. You would not live long enough to win the war. Why live ones life to just be a foot note on history. So you did what your brothers would not, You sold your avatar for true immortality. You joined the Assamites joining their sorccer caste. You supported the clan to the best of your ability. Then came the schisim, while many left because they fallowed the god of abrham, you had to leave because you followed older gods, the gods of creation and distruction. You fled with the schmatics, and have moved to mutiple camarilla cities, keeping your true reason for leaving the clan secret.",
          "",
          "",
          "",
          "",
          "",
          "",
          "",
          "POT"
        ],
        [
          "Staff Generated History"
        ],
        [],
        [
          "Sire:",
          "Murilia Bahri",
          "Reference: (If any)",
          "",
          "",
          "Clan",
          "Assamite \"Sorcerer\" - Magical Aura"
        ],
        [
          "Embrace Date:",
          "1320 A.D.",
          "Embrace Location:",
          "Dubi",
          "",
          "Generation",
          "Pretender Elder 8"
        ],
        [],
        [
          "Who You Know",
          "Your relationship to these people is described. This may mean they do not know you."
        ],
        [],
        [],
        [],
        [],
        [
          "Starting Goals",
          "These are recomendations, not mandates."
        ],
        [],
        [],
        [],
        [],
        [
          "Player Amended History",
          "",
          "Date Submited"
        ]
      ],
      "records": [
        {
          "staff_generated_concept": "You were a mage you controled reality and were a strong warrior in the wars of ascention. But then you learned the most demoralizing truth. You would not live long enough to win the war. Why live ones life to just be a foot note on history. So you did what your brothers would not, You sold your avatar for true immortality. You joined the Assamites joining their sorccer caste. You supported the clan to the best of your ability. Then came the schisim, while many left because they fallowed the god of abrham, you had to leave because you followed older gods, the gods of creation and distruction. You fled with the schmatics, and have moved to mutiple camarilla cities, keeping your true reason for leaving the clan secret.",
          "created_by": "POT"
        },
        {
          "staff_generated_concept": "Staff Generated History"
        },
        {
          "staff_generated_concept": "Sire:",
          "column_2": "Murilia Bahri",
          "column_3": "Reference: (If any)",
          "column_6": "Clan",
          "column_7": "Assamite \"Sorcerer\" - Magical Aura"
        },
        {
          "staff_generated_concept": "Embrace Date:",
          "column_2": "1320 A.D.",
          "column_3": "Embrace Location:",
          "column_4": "Dubi",
          "column_6": "Generation",
          "column_7": "Pretender Elder 8"
        },
        {
          "staff_generated_concept": "Who You Know",
          "column_2": "Your relationship to these people is described. This may mean they do not know you."
        },
        {
          "staff_generated_concept": "Starting Goals",
          "column_2": "These are recomendations, not mandates."
        },
        {
          "staff_generated_concept": "Player Amended History",
          "column_3": "Date Submited"
        }
      ]
    },
    "Blood Bonds  Valudrie": {
      "rows": [
        [
          "Valudrie / Blood Bond"
        ],
        [
          "Date:",
          "Name",
          "Pack Name",
          "Current Level"
        ]
      ],
      "records": []
    },
    "Personal Plot  Objects": {
      "rows": [
        [
          "Personal Plot / Objects",
          "Date",
          "ST For the Plot"
        ]
      ],
      "records": []
    },
    "Downtimes": {
      "rows": [
        [
          "Genaral Towntimes",
          "3.0",
          "Influnce Downtimes",
          "0",
          "Computer Downtimes",
          "0",
          "Science Downtimes",
          "0"
        ],
        [],
        [
          "Timestamp",
          "Score",
          "What is your Character's name?",
          "What clan (or supernatural) does your character belong?",
          "What is the player's name or your (facebook name if it is different)?",
          "Hunting Actions",
          "Hunting Modifications",
          "Investigation / Patrol Actions",
          "Purpose of Investigation / Patrol",
          "Blood Magic Research",
          "Elite Influnce Actions",
          "Underworld Influence Actions",
          "I have merits or flaws that affect my influences actions",
          "Science Downtime Actions",
          "Computer Downtimes Actions",
          "Is there an NPC you wish to contact?",
          "Do you still need to do this NPC interaction?",
          "Staff Mandated Actions",
          "Do you still need to do this Staff Mandated Action?",
          "I would like to buy this with my Experience",
          "How much xp am I spending?",
          "If it is an out of clan discipline or a secondary skill who is the teacher?"
        ]
      ],
      "records": [
        {
          "0": "Investigation / Patrol Actions",
          "genaral_towntimes": "Timestamp",
          "3_0": "Score",
          "influnce_downtimes": "What is your Character's name?",
          "computer_downtimes": "What is the player's name or your (facebook name if it is different)?",
          "science_downtimes": "Hunting Modifications",
          "column_9": "Purpose of Investigation / Patrol",
          "column_10": "Blood Magic Research",
          "column_11": "Elite Influnce Actions",
          "column_12": "Underworld Influence Actions",
          "column_13": "I have merits or flaws that affect my influences actions",
          "column_14": "Science Downtime Actions",
          "column_15": "Computer Downtimes Actions",
          "column_16": "Is there an NPC you wish to contact?",
          "column_17": "Do you still need to do this NPC interaction?",
          "column_18": "Staff Mandated Actions",
          "column_19": "Do you still need to do this Staff Mandated Action?",
          "column_20": "I would like to buy this with my Experience",
          "column_21": "How much xp am I spending?",
          "column_22": "If it is an out of clan discipline or a secondary skill who is the teacher?"
        }
      ]
    },
    "Submissions": {
      "rows": [
        [
          "Method:",
          "",
          "Date:"
        ],
        [],
        [
          "Method:",
          "",
          "Date:"
        ],
        [],
        [
          "Method:",
          "",
          "Date:"
        ],
        [],
        [
          "Method:",
          "",
          "Date:"
        ],
        [],
        [
          "Method:",
          "",
          "Date:"
        ],
        [],
        [
          "Method:",
          "",
          "Date:"
        ],
        [],
        [
          "Method:",
          "",
          "Date:"
        ],
        [],
        [
          "Method:",
          "",
          "Date:"
        ],
        [],
        [
          "Method:",
          "",
          "Date:"
        ],
        [],
        [
          "Method:",
          "",
          "Date:"
        ],
        [],
        [
          "Method:",
          "",
          "Date:"
        ],
        [],
        [
          "Method:",
          "",
          "Date:"
        ],
        [],
        [
          "Method:",
          "",
          "Date:"
        ],
        [],
        [
          "Method:",
          "",
          "Date:"
        ],
        [],
        [
          "Method:",
          "",
          "Date:"
        ],
        [],
        [
          "Method:",
          "",
          "Date:"
        ],
        [],
        [
          "Method:",
          "",
          "Date:"
        ],
        [],
        [
          "Method:",
          "",
          "Date:"
        ],
        [],
        [
          "Method:",
          "",
          "Date:"
        ],
        [],
        [
          "Method:",
          "",
          "Date:"
        ],
        [],
        [
          "Method:",
          "",
          "Date:"
        ],
        [],
        [
          "Method:",
          "",
          "Date:"
        ],
        [],
        [
          "Method:",
          "",
          "Date:"
        ],
        [],
        [
          "Method:",
          "",
          "Date:"
        ]
      ],
      "records": [
        {
          "method": "Method:",
          "date": "Date:"
        },
        {
          "method": "Method:",
          "date": "Date:"
        },
        {
          "method": "Method:",
          "date": "Date:"
        },
        {
          "method": "Method:",
          "date": "Date:"
        },
        {
          "method": "Method:",
          "date": "Date:"
        },
        {
          "method": "Method:",
          "date": "Date:"
        },
        {
          "method": "Method:",
          "date": "Date:"
        },
        {
          "method": "Method:",
          "date": "Date:"
        },
        {
          "method": "Method:",
          "date": "Date:"
        },
        {
          "method": "Method:",
          "date": "Date:"
        },
        {
          "method": "Method:",
          "date": "Date:"
        },
        {
          "method": "Method:",
          "date": "Date:"
        },
        {
          "method": "Method:",
          "date": "Date:"
        },
        {
          "method": "Method:",
          "date": "Date:"
        },
        {
          "method": "Method:",
          "date": "Date:"
        },
        {
          "method": "Method:",
          "date": "Date:"
        },
        {
          "method": "Method:",
          "date": "Date:"
        },
        {
          "method": "Method:",
          "date": "Date:"
        },
        {
          "method": "Method:",
          "date": "Date:"
        },
        {
          "method": "Method:",
          "date": "Date:"
        },
        {
          "method": "Method:",
          "date": "Date:"
        },
        {
          "method": "Method:",
          "date": "Date:"
        },
        {
          "method": "Method:",
          "date": "Date:"
        }
      ]
    }
  }
}
